meet_in_the_middle/__init__.py
meet_in_the_middle/app_test.py
meet_in_the_middle/batch_app_v2.py
meet_in_the_middle/batch_test_streamlit.py
meet_in_the_middle/map_app_test.py
meet_in_the_middle/streamlit_functions_batch_v2.py
meet_in_the_middle-0.1.0.dist-info/METADATA
meet_in_the_middle-0.1.0.dist-info/WHEEL
meet_in_the_middle-0.1.0.dist-info/RECORD
